{
  "generated_at_utc": "2025-08-14T17:51:55.897284+00:00",
  "hours_window": 12,
  "items": [
    {
      "channel": "Anatoxich",
      "title": "Find all secret ￼brainrot 🕵️ #brainrot",
      "url": "https://www.youtube.com/shorts/kpODguDRTVU",
      "published_at_utc": "2025-08-14T17:29:15+00:00",
      "age_seconds": 1346
    },
    {
      "channel": "Берлога T2x2",
      "title": "T2x2 СМОТРИТ: ВИТУБЕРЫ ПОПАЛИ В ЦИФРОВОЕ РАБСТВО | VShojo",
      "url": "https://www.youtube.com/watch?v=RVYKX9vSziE",
      "published_at_utc": "2025-08-14T17:22:40+00:00",
      "age_seconds": 1746
    },
    {
      "channel": "STAYA DRIFT",
      "title": "РЕНАТКО ПОКАЗАЛ СВОЮ НОВУЮ BMW M5 F10 1/200 EDITION !😱| ЭМОЦИИ ОТ BMW M5 E60 СТИЛА !",
      "url": "https://www.youtube.com/watch?v=dF8hBgikckk",
      "published_at_utc": "2025-08-14T17:20:52+00:00",
      "age_seconds": 1853
    },
    {
      "channel": "Anatoxich",
      "title": "Tung tung sahur balerina capuccina brainrot   #brainrot",
      "url": "https://www.youtube.com/shorts/ZVoNFPh-VbE",
      "published_at_utc": "2025-08-14T16:58:01+00:00",
      "age_seconds": 3220
    },
    {
      "channel": "WORLD TOP",
      "title": "Брат превратил дом в загадочный квест 😮",
      "url": "https://www.youtube.com/shorts/ZXGbwbJvhug",
      "published_at_utc": "2025-08-14T16:30:11+00:00",
      "age_seconds": 4890
    },
    {
      "channel": "курОлеся",
      "title": "Блевотня 😵🤢 #пов #мемы #юмор #жиза #скетч #тренд #тикток #pov",
      "url": "https://www.youtube.com/shorts/eOtR4Px3jYc",
      "published_at_utc": "2025-08-14T16:07:54+00:00",
      "age_seconds": 6236
    },
    {
      "channel": "курОлеся",
      "title": "Любимые звуки #пов #мемы #юмор #жиза #скетч #тренд #тикток #pov",
      "url": "https://www.youtube.com/shorts/aN3856yNtFQ",
      "published_at_utc": "2025-08-14T16:07:49+00:00",
      "age_seconds": 6241
    },
    {
      "channel": "курОлеся",
      "title": "И всё становится ясно… #пов #мемы #юмор #жиза #скетч #тренд #тикток #pov",
      "url": "https://www.youtube.com/shorts/2TslvyuZcA0",
      "published_at_utc": "2025-08-14T16:07:03+00:00",
      "age_seconds": 6287
    },
    {
      "channel": "курОлеся",
      "title": "Спасибо таким друзьям за заботу 🥹#пов #мемы #юмор #жиза #скетч #тренд #тикток #pov",
      "url": "https://www.youtube.com/shorts/vWuOTHkoCsU",
      "published_at_utc": "2025-08-14T16:06:11+00:00",
      "age_seconds": 6339
    },
    {
      "channel": "Max Maximov",
      "title": "Про двух королей",
      "url": "https://www.youtube.com/shorts/r_EnT0Gpv8k",
      "published_at_utc": "2025-08-14T16:04:32+00:00",
      "age_seconds": 6428
    },
    {
      "channel": "Max Maximov",
      "title": "Боги воды",
      "url": "https://www.youtube.com/shorts/gg7cVa20hWU",
      "published_at_utc": "2025-08-14T15:53:50+00:00",
      "age_seconds": 7070
    },
    {
      "channel": "Собиратель новостей",
      "title": "Хозяйка Принесла к Квартирантам ГРОБ С МАМОЙ",
      "url": "https://www.youtube.com/shorts/P-GTqJhz0hc",
      "published_at_utc": "2025-08-14T15:44:54+00:00",
      "age_seconds": 7616
    },
    {
      "channel": "EdisonPts",
      "title": "ПРЕДАТЕЛИ ВСЕГДА ИГРАЮТ С ВКЛЮЧЕННЫМИ ВЕБКАМИ В AMONG US МАЙНКРАФТ!",
      "url": "https://www.youtube.com/watch?v=F8aIEbK8Bd8",
      "published_at_utc": "2025-08-14T15:40:59+00:00",
      "age_seconds": 7849
    },
    {
      "channel": "Amitesh",
      "title": "Как добыть пресную воду из океана? #амитеш #выживание #океан #вода",
      "url": "https://www.youtube.com/shorts/0jGXuDZUwfY",
      "published_at_utc": "2025-08-14T15:38:34+00:00",
      "age_seconds": 7981
    },
    {
      "channel": "Новостной Гусь",
      "title": "Морской бриз",
      "url": "https://www.youtube.com/shorts/oTt716LrCIA",
      "published_at_utc": "2025-08-14T15:30:29+00:00",
      "age_seconds": 8478
    },
    {
      "channel": "Coffi Channel",
      "title": "СМЕХ ДО СЛЁЗ! УБЕГИ ОТ ТОРНАДО пока НЕ ПОЗДНО! ОЧЕНЬ ОПАСНАЯ ПУСТЫНЯ! ОБНОВЛЕНИЕ В PEAK",
      "url": "https://www.youtube.com/watch?v=VTPOL48Ygho",
      "published_at_utc": "2025-08-14T15:26:14+00:00",
      "age_seconds": 8733
    },
    {
      "channel": "Anatoxich",
      "title": "Pot hotspot 📲 brainrot steal a Brainrot 🔥 #brainrot #memes",
      "url": "https://www.youtube.com/shorts/_sS85cw-ykY",
      "published_at_utc": "2025-08-14T15:22:45+00:00",
      "age_seconds": 8936
    },
    {
      "channel": "FixEye - Роблокс",
      "title": "РАДУЖНЫЙ ПРЕДМЕТ ЗА 125 КУЛИНАРНЫХ СУНДУКОВ 🤯 | Фиксай #shorts",
      "url": "https://www.youtube.com/shorts/aYTnMnGuPS8",
      "published_at_utc": "2025-08-14T15:21:09+00:00",
      "age_seconds": 9041
    },
    {
      "channel": "WORLD TOP",
      "title": "Он решил проверь, что произойдет с ним под водой 😮",
      "url": "https://www.youtube.com/shorts/vP4SP_fkBrY",
      "published_at_utc": "2025-08-14T15:15:16+00:00",
      "age_seconds": 9385
    },
    {
      "channel": "Bobik Stories | Лучшие Видео Со Всего Мира",
      "title": "Эти Настройки У Них С Рождения ⚙️👶✅",
      "url": "https://www.youtube.com/shorts/_2zXcI4smG4",
      "published_at_utc": "2025-08-14T15:15:04+00:00",
      "age_seconds": 9400
    },
    {
      "channel": "Мир милых животных 🦔",
      "title": "Вот так кошки учиться доверять людям 🐈🥺#милыеживотные #животные",
      "url": "https://www.youtube.com/shorts/6_G6ihrPBlI",
      "published_at_utc": "2025-08-14T15:13:01+00:00",
      "age_seconds": 9514
    },
    {
      "channel": "Коннор",
      "title": "Проверил, как вам?",
      "url": "https://www.youtube.com/shorts/U423-hC8w6c",
      "published_at_utc": "2025-08-14T15:08:46+00:00",
      "age_seconds": 9774
    },
    {
      "channel": "ZOMBIERUS",
      "title": "СТАРТ ВТОРОГО ЭТАПА БЕТЫ BATTLEFIELD 6 \\\\ НОВАЯ КАРТА и РЕЖИМЫ",
      "url": "https://www.youtube.com/watch?v=i1iqqxB904c",
      "published_at_utc": "2025-08-14T15:01:10+00:00",
      "age_seconds": 10224
    },
    {
      "channel": "Recrent",
      "title": "PUBG УЖЕ НЕ БУДЕТ ПРЕЖНИМ",
      "url": "https://www.youtube.com/watch?v=Z69STR4RRoQ",
      "published_at_utc": "2025-08-14T15:00:23+00:00",
      "age_seconds": 10287
    },
    {
      "channel": "Kuplinov ► Play",
      "title": "ОТДАВАЙ ДЕНЬГИ! ► Mafia: The Old Country #3",
      "url": "https://www.youtube.com/watch?v=Cy07h6eau4c",
      "published_at_utc": "2025-08-14T15:00:22+00:00",
      "age_seconds": 10280
    },
    {
      "channel": "Anatoxich",
      "title": "Brainrot voice activation ￼challenge 🗿 #brainrot",
      "url": "https://www.youtube.com/shorts/-UPRZGZwkQo",
      "published_at_utc": "2025-08-14T15:00:07+00:00",
      "age_seconds": 10294
    },
    {
      "channel": "This is Хорошо",
      "title": "КАК В КИТАЙСКОМ СУДЕ ДЕЛИЛИ 29 КУРИЦ ПОПОЛАМ | Почему «умные» авто делают водителей тупее?",
      "url": "https://www.youtube.com/watch?v=uvIHDeYtun0",
      "published_at_utc": "2025-08-14T14:52:47+00:00",
      "age_seconds": 10731
    },
    {
      "channel": "Khavr",
      "title": "ОЛИГАРХИ БРОСИЛИ СВОИ СУПЕРКАРЫ В МОСКВЕ!",
      "url": "https://www.youtube.com/watch?v=8i8jFRaZhCk",
      "published_at_utc": "2025-08-14T14:49:12+00:00",
      "age_seconds": 10962
    },
    {
      "channel": "STAYA DRIFT",
      "title": "РЕНАТКО ВСТРЕТИЛ СТИЛА НА BMW M5 E60 В ГРУЗИИ !⚡| ОБЗОР НА САМЫЙ ДОРОГОЙ ОСОБНЯК !",
      "url": "https://www.youtube.com/watch?v=G6Wz8xnWOpk",
      "published_at_utc": "2025-08-14T14:40:07+00:00",
      "age_seconds": 11498
    },
    {
      "channel": "FixEye - Роблокс",
      "title": "Как 100% Получить Дивайн в Grow a Garden 🤣 | Фиксай #shorts",
      "url": "https://www.youtube.com/shorts/zg6ZfrO3IyY",
      "published_at_utc": "2025-08-14T14:35:20+00:00",
      "age_seconds": 11790
    },
    {
      "channel": "Anatoxich",
      "title": "Tralalero tralala danger brainrot ⚠️⚠️⚠️ #brainrot",
      "url": "https://www.youtube.com/shorts/ApsGpSJWZrw",
      "published_at_utc": "2025-08-14T14:33:49+00:00",
      "age_seconds": 11872
    },
    {
      "channel": "Amitesh",
      "title": "Древняя форма укладки камня #амитеш #технологии #история",
      "url": "https://www.youtube.com/shorts/i51sOtfSW0g",
      "published_at_utc": "2025-08-14T14:30:25+00:00",
      "age_seconds": 12070
    },
    {
      "channel": "Margaritka",
      "title": "Карман для дырок 🤣🤣",
      "url": "https://www.youtube.com/shorts/pqdA0EbFO5c",
      "published_at_utc": "2025-08-14T14:18:51+00:00",
      "age_seconds": 12775
    },
    {
      "channel": "Max Maximov",
      "title": "Про дверь",
      "url": "https://www.youtube.com/shorts/8zfWB31QZok",
      "published_at_utc": "2025-08-14T14:16:30+00:00",
      "age_seconds": 12910
    },
    {
      "channel": "MemesFF",
      "title": "#мемы #memes #mems #mem #shorts #youtubeshorts #мемчик #вирусно #веселое #мем #мемасы #memsff",
      "url": "https://www.youtube.com/shorts/O7SQcoAQ61k",
      "published_at_utc": "2025-08-14T14:15:06+00:00",
      "age_seconds": 13007
    },
    {
      "channel": "Берлога T2x2",
      "title": "БОРЬБА С САМИМ СОБОЙ 😄 #t2x2 #реакция #юмор #история #мем",
      "url": "https://www.youtube.com/shorts/q8mSdTA-Aas",
      "published_at_utc": "2025-08-14T14:14:11+00:00",
      "age_seconds": 13055
    },
    {
      "channel": "Max Maximov",
      "title": "Клонировать динозавров",
      "url": "https://www.youtube.com/shorts/sX51nLqxBPU",
      "published_at_utc": "2025-08-14T14:02:25+00:00",
      "age_seconds": 13755
    },
    {
      "channel": "Авто.Бот",
      "title": "Тюнинг Мерседес Менсори vs Брабус 🤯",
      "url": "https://www.youtube.com/shorts/IhhYY5Wpn3w",
      "published_at_utc": "2025-08-14T14:00:25+00:00",
      "age_seconds": 13864
    },
    {
      "channel": "Майни",
      "title": "Точка Невозврата #80 - 84 ВОЗМЕЗДИЕ: КОНЕЦ [Отец Тадмавриэль] - ЖИВОЙ ПОКОЙНИК • Майнкрафт | Реакция",
      "url": "https://www.youtube.com/watch?v=H8yXO0Fgk1M",
      "published_at_utc": "2025-08-14T14:00:23+00:00",
      "age_seconds": 13867
    },
    {
      "channel": "Гохисыч",
      "title": "Как медленный шар мальчика победил всех #shorts",
      "url": "https://www.youtube.com/shorts/3qLYNtJRfkk",
      "published_at_utc": "2025-08-14T14:00:11+00:00",
      "age_seconds": 13892
    },
    {
      "channel": "KinoLayk",
      "title": "Своими руками сделал квок из ложки",
      "url": "https://www.youtube.com/shorts/lE_hLxPBEIE",
      "published_at_utc": "2025-08-14T13:58:21+00:00",
      "age_seconds": 13998
    },
    {
      "channel": "Margaritka",
      "title": "Разделили раскраску 😄",
      "url": "https://www.youtube.com/shorts/6HR3fIt26KQ",
      "published_at_utc": "2025-08-14T13:40:49+00:00",
      "age_seconds": 15057
    },
    {
      "channel": "Quantum Games",
      "title": "ВЫЖИВАНИЕ НА ОСТРОВЕ С 0$ ДЕНЕГ НА ФЕРМЕ!!! ДЕНЬ: 1",
      "url": "https://www.youtube.com/watch?v=ZFMeiwHQ3JA",
      "published_at_utc": "2025-08-14T13:39:19+00:00",
      "age_seconds": 15133
    },
    {
      "channel": "Сергей Милушкин",
      "title": "Он думал что никто не видит",
      "url": "https://www.youtube.com/shorts/kDs_-jLqids",
      "published_at_utc": "2025-08-14T13:29:42+00:00",
      "age_seconds": 15711
    },
    {
      "channel": "Amitesh",
      "title": "Каноба - древнее орудие самураев #амитеш #самурай #история",
      "url": "https://www.youtube.com/shorts/QtI_zMEvoiA",
      "published_at_utc": "2025-08-14T13:28:11+00:00",
      "age_seconds": 15804
    },
    {
      "channel": "Anatoxich",
      "title": "Легендарный те те те саур в укради брейнрот  #brainrot #roblox",
      "url": "https://www.youtube.com/shorts/Pa5iWbREXLw",
      "published_at_utc": "2025-08-14T13:27:34+00:00",
      "age_seconds": 15847
    },
    {
      "channel": "Max Maximov",
      "title": "Кого любят больше?",
      "url": "https://www.youtube.com/shorts/Wgdh_5vgHjc",
      "published_at_utc": "2025-08-14T13:21:01+00:00",
      "age_seconds": 16239
    },
    {
      "channel": "Max Maximov",
      "title": "Спасает друга",
      "url": "https://www.youtube.com/shorts/SWBcuh_23p4",
      "published_at_utc": "2025-08-14T13:05:22+00:00",
      "age_seconds": 17178
    },
    {
      "channel": "WORLD TOP",
      "title": "Все подумали, что это конец для него 😮",
      "url": "https://www.youtube.com/shorts/GcDdwXDzJrw",
      "published_at_utc": "2025-08-14T13:05:00+00:00",
      "age_seconds": 17201
    },
    {
      "channel": "IGM",
      "title": "В COUNTER-STRIKE ДОБАВЯТ СКИНЫ НА КУРИЦ",
      "url": "https://www.youtube.com/shorts/PuWNPRnUQew",
      "published_at_utc": "2025-08-14T13:00:45+00:00",
      "age_seconds": 17444
    },
    {
      "channel": "TWITCHFM",
      "title": "Топ Моменты с Twitch | Шведская Семья",
      "url": "https://www.youtube.com/watch?v=4bJIcVkmkZs",
      "published_at_utc": "2025-08-14T13:00:07+00:00",
      "age_seconds": 17505
    },
    {
      "channel": "ГЛЕНТ",
      "title": "Посадил ТОЛЬКО БАМБУК В Вырасти САД! $30 000 РОБУКСОВ НА СЕМЕНА в РОБЛОКС!",
      "url": "https://www.youtube.com/watch?v=nHEvIcLPYfg",
      "published_at_utc": "2025-08-14T13:00:03+00:00",
      "age_seconds": 17489
    },
    {
      "channel": "Наташа и Вова",
      "title": "Стакан в стакан #challenge #games #игры #веселыеигры #fungame #funnygames",
      "url": "https://www.youtube.com/shorts/Zs2QwEQ8a9k",
      "published_at_utc": "2025-08-14T12:43:46+00:00",
      "age_seconds": 18473
    },
    {
      "channel": "Max Maximov",
      "title": "Плавать весело",
      "url": "https://www.youtube.com/shorts/--k-L6-lIjQ",
      "published_at_utc": "2025-08-14T12:31:37+00:00",
      "age_seconds": 19203
    },
    {
      "channel": "Sherl0ck",
      "title": "💪БЫСТРАЯ ТРЕНИРОВКА!💪| #Sherl0ck #Shorts #кс #cs #csgolive #cs2 #csgo #counterstrike",
      "url": "https://www.youtube.com/shorts/Tz1Wkd2saUQ",
      "published_at_utc": "2025-08-14T12:30:39+00:00",
      "age_seconds": 19265
    },
    {
      "channel": "Риса за Творчество",
      "title": "Катаемся с Еатом 🎪 #Yeat #DANGEROUSSUMMER #PUTITONG #разбор #рзт #рисазатворчество",
      "url": "https://www.youtube.com/shorts/jhRLZ2urk0c",
      "published_at_utc": "2025-08-14T12:24:47+00:00",
      "age_seconds": 19612
    },
    {
      "channel": "Настя, это где?",
      "title": "😳 ВСЕ ЗАБЫЛИ ПРО МОЙ ДР",
      "url": "https://www.youtube.com/shorts/1xdmOxDyxrA",
      "published_at_utc": "2025-08-14T12:14:03+00:00",
      "age_seconds": 20261
    },
    {
      "channel": "Мир милых животных 🦔",
      "title": "Нашел этого малыша совсем одного 🦁🥺 #милыеживотные #животные",
      "url": "https://www.youtube.com/shorts/NkYoujcVPLc",
      "published_at_utc": "2025-08-14T12:14:00+00:00",
      "age_seconds": 20255
    },
    {
      "channel": "Смешновости",
      "title": "Самый крутой скрипач 😂 #истории #история #новости #новость #shorts",
      "url": "https://www.youtube.com/shorts/uKwYgVPt2q8",
      "published_at_utc": "2025-08-14T12:01:40+00:00",
      "age_seconds": 21002
    },
    {
      "channel": "Майни",
      "title": "Я смотрел VK Видео 30 дней - и вот что со мной стало... | Реакция",
      "url": "https://www.youtube.com/watch?v=ucda_EE7dEM",
      "published_at_utc": "2025-08-14T12:01:27+00:00",
      "age_seconds": 21003
    },
    {
      "channel": "Компот",
      "title": "Я СДЕЛАЛ РЕМОНТ В ДОМЕ СТРАННОГО ЖИТЕЛЯ В МАЙНКРАФТ | Компот Minecraft",
      "url": "https://www.youtube.com/watch?v=JQtUz5FyZcw",
      "published_at_utc": "2025-08-14T12:00:39+00:00",
      "age_seconds": 21076
    },
    {
      "channel": "Enderestories",
      "title": "В его жизни появился домашний питомец!",
      "url": "https://www.youtube.com/shorts/LIZk9oTn7bo",
      "published_at_utc": "2025-08-14T11:50:00+00:00",
      "age_seconds": 21703
    },
    {
      "channel": "Amitesh",
      "title": "Робо-пчела #амитеш #технологии #робот",
      "url": "https://www.youtube.com/shorts/oSqPpBIjhh0",
      "published_at_utc": "2025-08-14T11:49:53+00:00",
      "age_seconds": 21702
    },
    {
      "channel": "WORLD TOP",
      "title": "Они думали, что легко выйдет, но не вышло 😳",
      "url": "https://www.youtube.com/shorts/49NenFKFPNM",
      "published_at_utc": "2025-08-14T11:45:00+00:00",
      "age_seconds": 22001
    },
    {
      "channel": "Тимур Сидельников",
      "title": "Провальные очереди за новыми iPhone",
      "url": "https://www.youtube.com/shorts/3KsuEY61wWw",
      "published_at_utc": "2025-08-14T11:40:08+00:00",
      "age_seconds": 22295
    },
    {
      "channel": "CS2TV",
      "title": "ТРАНСФЕР ГОДА! ЧТО БУДЕТ СО SPIRIT ПОСЛЕ УХОДА ЗОНТИКСА? ПЛЮСЫ И МИНУСЫ ТНИРА - @CS2TVNEWS​",
      "url": "https://www.youtube.com/watch?v=ZIoePP_QuWA",
      "published_at_utc": "2025-08-14T11:32:55+00:00",
      "age_seconds": 22722
    },
    {
      "channel": "Antochi",
      "title": "Мне хотели заплатить за ПРОПАГАНДУ ранней беременности...",
      "url": "https://www.youtube.com/watch?v=JvPGrMSeVIo",
      "published_at_utc": "2025-08-14T11:16:00+00:00",
      "age_seconds": 23736
    },
    {
      "channel": "Глеб Рандалайнен",
      "title": "Как Избавиться От Комаров 🦟",
      "url": "https://www.youtube.com/shorts/dhdeQnjftCs",
      "published_at_utc": "2025-08-14T11:03:11+00:00",
      "age_seconds": 24508
    },
    {
      "channel": "Короче, новости",
      "title": "В России Требуют Запретить ИРАНСКУЮ ТОНИРОВКУ",
      "url": "https://www.youtube.com/shorts/3B8tooF51ss",
      "published_at_utc": "2025-08-14T11:00:09+00:00",
      "age_seconds": 24691
    },
    {
      "channel": "KinoLayk",
      "title": "Примагнитило к земле",
      "url": "https://www.youtube.com/shorts/GAjmJz2ZHKM",
      "published_at_utc": "2025-08-14T10:50:29+00:00",
      "age_seconds": 25270
    },
    {
      "channel": "МайорКрафт",
      "title": "Самое вкусное пирожное #фильм #сериал #моменты",
      "url": "https://www.youtube.com/shorts/rdnSSwom5nM",
      "published_at_utc": "2025-08-14T10:45:04+00:00",
      "age_seconds": 25589
    },
    {
      "channel": "TreshFilms",
      "title": "Видит будущее каждого человека 😁 #фильм #сериал #моменты #shorts",
      "url": "https://www.youtube.com/shorts/7cUinrZtim4",
      "published_at_utc": "2025-08-14T10:45:02+00:00",
      "age_seconds": 25589
    },
    {
      "channel": "Гохисыч",
      "title": "Она просила попкорн, а получала всё что угодно, кроме него #shorts",
      "url": "https://www.youtube.com/shorts/EpnxlbMC5uw",
      "published_at_utc": "2025-08-14T10:45:02+00:00",
      "age_seconds": 25601
    },
    {
      "channel": "Гохисыч",
      "title": "Зачем врачи используют этот странный предмет #shorts",
      "url": "https://www.youtube.com/shorts/tbhv7xj3cpI",
      "published_at_utc": "2025-08-14T10:15:11+00:00",
      "age_seconds": 27392
    },
    {
      "channel": "Enderestories",
      "title": "Парень долго ждал этого момента! / @iamjustbait",
      "url": "https://www.youtube.com/shorts/0aqdUo1IFZA",
      "published_at_utc": "2025-08-14T10:10:00+00:00",
      "age_seconds": 27703
    },
    {
      "channel": "ANAR CHILL",
      "title": "ОБЗОР НА ВОЕННУЮ ТЕХНИКУ С КРАСОТКОЙ | ПРОКАТИЛИ НА ТАНКЕ",
      "url": "https://www.youtube.com/watch?v=nSMiUGE0Dcg",
      "published_at_utc": "2025-08-14T10:04:21+00:00",
      "age_seconds": 28030
    },
    {
      "channel": "Новостной Гусь",
      "title": "Так просто телефон не отдаст",
      "url": "https://www.youtube.com/shorts/wCndbKWGunU",
      "published_at_utc": "2025-08-14T10:01:37+00:00",
      "age_seconds": 28210
    },
    {
      "channel": "Holy Baam",
      "title": "99% Зрителей Не Угадают Какой Секретный Брейнрот Мне выпадет из Лаки Блока",
      "url": "https://www.youtube.com/shorts/koowp3VGf_U",
      "published_at_utc": "2025-08-14T10:01:18+00:00",
      "age_seconds": 28236
    },
    {
      "channel": "Смешновости",
      "title": "Крутой фокус 😲 #истории #история #новости #новость #shorts",
      "url": "https://www.youtube.com/shorts/jbiW9Qg8Gdc",
      "published_at_utc": "2025-08-14T10:01:15+00:00",
      "age_seconds": 28227
    },
    {
      "channel": "Goryachev",
      "title": "Я ПРОЖИЛ 2000 ДНЕЙ В 99 НОЧЕЙ В ЛЕСУ РОБЛОКС! 99 NIGHT IN THE FOREST В ROBLOX",
      "url": "https://www.youtube.com/shorts/gsB44LSH8nw",
      "published_at_utc": "2025-08-14T10:01:11+00:00",
      "age_seconds": 28227
    },
    {
      "channel": "Алежа Обухов",
      "title": "Та самая бабка, которая сдаёт комнату студентам. Часть 3",
      "url": "https://www.youtube.com/shorts/aoqGsf9854E",
      "published_at_utc": "2025-08-14T10:00:27+00:00",
      "age_seconds": 28265
    },
    {
      "channel": "ДУШНИЛА",
      "title": "ДУШНИЛА № 85",
      "url": "https://www.youtube.com/shorts/0DcIT_IELL8",
      "published_at_utc": "2025-08-14T09:51:48+00:00",
      "age_seconds": 28803
    },
    {
      "channel": "Гохисыч",
      "title": "Что скрывалось под песком на пляже — она не поверила своим глазам #shorts",
      "url": "https://www.youtube.com/shorts/NLpF-U9Lavg",
      "published_at_utc": "2025-08-14T09:50:32+00:00",
      "age_seconds": 28871
    },
    {
      "channel": "Enderestories",
      "title": "Два атлета решили показать свои силы в соревновании! / @bwvine",
      "url": "https://www.youtube.com/shorts/pPcm3iW8b7A",
      "published_at_utc": "2025-08-14T09:25:00+00:00",
      "age_seconds": 30403
    },
    {
      "channel": "Мир милых животных 🦔",
      "title": "Вы удивитесь этому животному! 😍😱 #милыеживотные #животные",
      "url": "https://www.youtube.com/shorts/k0w1tHd7liQ",
      "published_at_utc": "2025-08-14T09:12:00+00:00",
      "age_seconds": 31175
    },
    {
      "channel": "EroxBlox",
      "title": "😱Я получил АДМИН КОМАНДЫ в Grow a Garden! ВЫДАЛ СЕБЕ JANDEL MONKEY и КИТСУНЕ В ВЫРАСТИ САД",
      "url": "https://www.youtube.com/watch?v=Pzv-8IgkzlU",
      "published_at_utc": "2025-08-14T09:08:55+00:00",
      "age_seconds": 31376
    },
    {
      "channel": "Короче, новости",
      "title": "Зумеры Соскуфились: mp3 плееры Вместо Spotify",
      "url": "https://www.youtube.com/shorts/qkk9uBedcpA",
      "published_at_utc": "2025-08-14T09:01:19+00:00",
      "age_seconds": 31821
    },
    {
      "channel": "FixEye - Роблокс",
      "title": "😱БИТВА 100 КУЛИНАРНЫХ СУНДУКОВ С УДАЧЕЙ АДМИНА! ФИКСАЙ ПРОТИВ АКАКИЯ в Grow a Garden!",
      "url": "https://www.youtube.com/watch?v=oEB5bMcB_PM",
      "published_at_utc": "2025-08-14T09:01:14+00:00",
      "age_seconds": 31836
    },
    {
      "channel": "Bobik Stories | Лучшие Видео Со Всего Мира",
      "title": "Искусственный Интеллект Рассказал, Кто Такая Жена 🤖💍🗣️",
      "url": "https://www.youtube.com/shorts/XjzZx4vIA_s",
      "published_at_utc": "2025-08-14T09:00:47+00:00",
      "age_seconds": 31857
    },
    {
      "channel": "WORLD TOP",
      "title": "Никто не верил, что у него выйдет 😮",
      "url": "https://www.youtube.com/shorts/JUfpNovZiqE",
      "published_at_utc": "2025-08-14T09:00:25+00:00",
      "age_seconds": 31876
    },
    {
      "channel": "Собиратель новостей",
      "title": "Трамп Затащил ПУТИНА на Военную Базу США",
      "url": "https://www.youtube.com/shorts/Al7MJeXfyyE",
      "published_at_utc": "2025-08-14T09:00:12+00:00",
      "age_seconds": 31898
    },
    {
      "channel": "Гохисыч",
      "title": "Заснул на лодке и пожалел об этом #shorts",
      "url": "https://www.youtube.com/shorts/RqQjqalOLEY",
      "published_at_utc": "2025-08-14T08:50:07+00:00",
      "age_seconds": 32496
    },
    {
      "channel": "Глеб Рандалайнен",
      "title": "Галаго 🙈 Заводить Или Нет?",
      "url": "https://www.youtube.com/shorts/NsbluDdy5bU",
      "published_at_utc": "2025-08-14T08:39:14+00:00",
      "age_seconds": 33145
    },
    {
      "channel": "Гохисыч",
      "title": "Необычный способ успокоить ребёнка #shorts",
      "url": "https://www.youtube.com/shorts/5b3nAiz7QIE",
      "published_at_utc": "2025-08-14T08:15:30+00:00",
      "age_seconds": 34573
    },
    {
      "channel": "ПОСЛЕДНЯЯ ИЗВИЛИНА",
      "title": "Ситуация в доминос",
      "url": "https://www.youtube.com/shorts/VOWpaqDXC4c",
      "published_at_utc": "2025-08-14T08:11:04+00:00",
      "age_seconds": 34839
    },
    {
      "channel": "Новостной Гусь",
      "title": "И где эта канатная дорога?",
      "url": "https://www.youtube.com/shorts/qaW5zRDnOoY",
      "published_at_utc": "2025-08-14T08:01:01+00:00",
      "age_seconds": 35446
    },
    {
      "channel": "Enderestories",
      "title": "Это один из самый сложных аттракционов в мире! / @winnereverytime",
      "url": "https://www.youtube.com/shorts/ZAdcEAwkqXI",
      "published_at_utc": "2025-08-14T08:00:38+00:00",
      "age_seconds": 35465
    },
    {
      "channel": "Holy Baam",
      "title": "КУПИЛ 9999999999Х УДАЧИ И ПОЛУЧИЛ СЕКРЕТНЫХ БРЕЙНРОТОВ ИЗ ГИПЕР ЯЩИКА В РОБЛОКС!",
      "url": "https://www.youtube.com/watch?v=68ELNHxX5Ts",
      "published_at_utc": "2025-08-14T08:00:10+00:00",
      "age_seconds": 35504
    },
    {
      "channel": "Смешновости",
      "title": "Приносит камушек 😂 #истории #история #новости #новость #shorts",
      "url": "https://www.youtube.com/shorts/-zyrU-DlfYI",
      "published_at_utc": "2025-08-14T08:00:00+00:00",
      "age_seconds": 35502
    },
    {
      "channel": "WORLD TOP",
      "title": "Когда впервые купила дорогое кофе 😳",
      "url": "https://www.youtube.com/shorts/vvmeH91TQDs",
      "published_at_utc": "2025-08-14T07:10:01+00:00",
      "age_seconds": 38500
    },
    {
      "channel": "MemesFF",
      "title": "#мемы #memes #mems #mem #shorts #youtubeshorts #мемчик #вирусно #веселое #мем #мемасы #memsff",
      "url": "https://www.youtube.com/shorts/x83TTGn0MKk",
      "published_at_utc": "2025-08-14T07:00:55+00:00",
      "age_seconds": 39058
    },
    {
      "channel": "shhenu",
      "title": "Это лучшее сочетание модов!",
      "url": "https://www.youtube.com/shorts/hVA08vCdixI",
      "published_at_utc": "2025-08-14T07:00:45+00:00",
      "age_seconds": 39061
    },
    {
      "channel": "Короче, новости",
      "title": "Биток Стал Дороже Гугла",
      "url": "https://www.youtube.com/shorts/5vcHkWCXlUw",
      "published_at_utc": "2025-08-14T06:56:52+00:00",
      "age_seconds": 39288
    },
    {
      "channel": "Короче, новости",
      "title": "Лебедев в 11й Раз Стал Отцом",
      "url": "https://www.youtube.com/shorts/MrIhHOILPC0",
      "published_at_utc": "2025-08-14T06:55:26+00:00",
      "age_seconds": 39374
    },
    {
      "channel": "Enderestories",
      "title": "Она спасла всех, кроме себя... / @yoaleismar",
      "url": "https://www.youtube.com/shorts/v24JpoLm_Aw",
      "published_at_utc": "2025-08-14T06:30:15+00:00",
      "age_seconds": 40888
    },
    {
      "channel": "Гохисыч",
      "title": "Невозможно найти номер 240? Это ловушка #shorts",
      "url": "https://www.youtube.com/shorts/eDzZw-yHgIM",
      "published_at_utc": "2025-08-14T06:17:29+00:00",
      "age_seconds": 41654
    },
    {
      "channel": "Мир милых животных 🦔",
      "title": "Особенный щенок по имени Муму 🐶🥹 #милыеживотные #животные",
      "url": "https://www.youtube.com/shorts/ZglnNjp4Wqo",
      "published_at_utc": "2025-08-14T06:14:00+00:00",
      "age_seconds": 41855
    },
    {
      "channel": "KinoLayk",
      "title": "Передал привет своей учительнице",
      "url": "https://www.youtube.com/shorts/ZiREvEsY0jM",
      "published_at_utc": "2025-08-14T06:00:27+00:00",
      "age_seconds": 42672
    }
  ]
}