{
  "generated_at_utc": "2025-08-12T12:30:36.923176+00:00",
  "hours_window": 3,
  "items": [
    {
      "channel": "Enderestories",
      "title": "Зачем она собирает морскую воду?",
      "url": "https://www.youtube.com/shorts/EGqiWrehNKk",
      "published_at_utc": "2025-08-12T11:30:20+00:00",
      "age_seconds": 3564
    },
    {
      "channel": "Гохисыч",
      "title": "Странная находка в озере озадачила девушку #shorts",
      "url": "https://www.youtube.com/shorts/xpEh1DYj8TU",
      "published_at_utc": "2025-08-12T11:49:37+00:00",
      "age_seconds": 2409
    },
    {
      "channel": "Гохисыч",
      "title": "Парень спрятал сюрприз в QR-кодах и подловил девушку #shorts credit (@andrey_sorokinn Ig)",
      "url": "https://www.youtube.com/shorts/bsKrF1ChVcQ",
      "published_at_utc": "2025-08-12T11:15:08+00:00",
      "age_seconds": 4478
    },
    {
      "channel": "Гохисыч",
      "title": "Папа включил дочке любимую песню и её реакция покорила всех #shorts",
      "url": "https://www.youtube.com/shorts/9DcKl8uw2b0",
      "published_at_utc": "2025-08-12T10:47:28+00:00",
      "age_seconds": 6138
    },
    {
      "channel": "MovieTop",
      "title": "Отряд самоубийц 2 #фильмы #фантастика #кино",
      "url": "https://www.youtube.com/shorts/yrwH-B0m6Yg",
      "published_at_utc": "2025-08-12T11:55:34+00:00",
      "age_seconds": 2054
    },
    {
      "channel": "Майни",
      "title": "ТАЙНОЕ МИРОВОЕ ПРАВИТЕЛЬСТВО [Топ Сикрет] ► Utopia Show | Реакция",
      "url": "https://www.youtube.com/watch?v=W0UnjTLvFi8",
      "published_at_utc": "2025-08-12T12:00:57+00:00",
      "age_seconds": 1732
    },
    {
      "channel": "KinoLayk",
      "title": "Работа над ошибками с добычей",
      "url": "https://www.youtube.com/shorts/U1tCmqvF0mQ",
      "published_at_utc": "2025-08-12T10:00:54+00:00",
      "age_seconds": 8936
    },
    {
      "channel": "Новостной Гусь",
      "title": "И все равно они милашки",
      "url": "https://www.youtube.com/shorts/1S0ah0gsjoM",
      "published_at_utc": "2025-08-12T10:25:00+00:00",
      "age_seconds": 7495
    },
    {
      "channel": "Max Maximov",
      "title": "Бой мыши с котами",
      "url": "https://www.youtube.com/shorts/uJq1RaoJYso",
      "published_at_utc": "2025-08-12T11:31:13+00:00",
      "age_seconds": 3527
    },
    {
      "channel": "Max Maximov",
      "title": "Любовь между кошкой и мышью",
      "url": "https://www.youtube.com/shorts/VztzIPwVuVQ",
      "published_at_utc": "2025-08-12T11:11:05+00:00",
      "age_seconds": 4735
    },
    {
      "channel": "Короче, новости",
      "title": "Старбакс Выгоняет Удалёнщиков из Кафе",
      "url": "https://www.youtube.com/shorts/nNwEPorDbsI",
      "published_at_utc": "2025-08-12T10:01:33+00:00",
      "age_seconds": 8912
    },
    {
      "channel": "Мир милых животных 🦔",
      "title": "Даже лошади нуждаются в парикмахерах 😨 ✂️ #милыеживотные #животные",
      "url": "https://www.youtube.com/shorts/8gIuVuUpNng",
      "published_at_utc": "2025-08-12T12:13:00+00:00",
      "age_seconds": 1030
    },
    {
      "channel": "kinoluv",
      "title": "Персы закрыли небо стрелами😳",
      "url": "https://www.youtube.com/shorts/3hIzwfnO-s0",
      "published_at_utc": "2025-08-12T11:50:47+00:00",
      "age_seconds": 2366
    },
    {
      "channel": "Bobik Stories | Лучшие Видео Со Всего Мира",
      "title": "Он Рассказал О Главном Правиле В Жизни 🧠📜✅",
      "url": "https://www.youtube.com/shorts/CvYf49bEQZY",
      "published_at_utc": "2025-08-12T10:21:04+00:00",
      "age_seconds": 7752
    },
    {
      "channel": "TreshFilms",
      "title": "Когда решил сделать доброе дело 🐮 #фильм #сериал #моменты #shorts",
      "url": "https://www.youtube.com/shorts/OSAPJMtmms0",
      "published_at_utc": "2025-08-12T10:45:06+00:00",
      "age_seconds": 6311
    },
    {
      "channel": "Глеб Рандалайнен",
      "title": "Ленивец 🦥 Медленный но Крутой",
      "url": "https://www.youtube.com/shorts/cXOBeS4pcAk",
      "published_at_utc": "2025-08-12T09:50:11+00:00",
      "age_seconds": 9606
    },
    {
      "channel": "НОВОСТНИЧОК",
      "title": "🤣 Хотел записать песню под гитару, но всё пошло не по плану! | Новостничок",
      "url": "https://www.youtube.com/shorts/paflO8C0eUY",
      "published_at_utc": "2025-08-12T11:45:07+00:00",
      "age_seconds": 2712
    },
    {
      "channel": "Смешновости",
      "title": "Зато сохранила напиток 😂 #истории #история #новости #новость #shorts",
      "url": "https://www.youtube.com/shorts/T0p3O5OBVzk",
      "published_at_utc": "2025-08-12T12:00:51+00:00",
      "age_seconds": 1771
    },
    {
      "channel": "Смешновости",
      "title": "Кинул мячик 😂 #истории #история #новости #новость #shorts",
      "url": "https://www.youtube.com/shorts/aFtohHtVzzo",
      "published_at_utc": "2025-08-12T10:00:00+00:00",
      "age_seconds": 9022
    },
    {
      "channel": "Amitesh",
      "title": "Антигравитационный стол #амитеш #физика #столы",
      "url": "https://www.youtube.com/shorts/d6AG_5B00tY",
      "published_at_utc": "2025-08-12T12:13:43+00:00",
      "age_seconds": 1000
    },
    {
      "channel": "МайорКрафт",
      "title": "Не такого он ждал зятя #фильм #сериал #моменты",
      "url": "https://www.youtube.com/shorts/Kabx85N44l4",
      "published_at_utc": "2025-08-12T10:45:04+00:00",
      "age_seconds": 6320
    },
    {
      "channel": "ДУШНИЛА",
      "title": "ДУШНИЛА № 83",
      "url": "https://www.youtube.com/shorts/4Vf3keQGB5g",
      "published_at_utc": "2025-08-12T11:59:17+00:00",
      "age_seconds": 1868
    },
    {
      "channel": "ПРЕМИЯ ДАРВИНА",
      "title": "Что думаете?",
      "url": "https://www.youtube.com/shorts/N9-0IBt1K_Q",
      "published_at_utc": "2025-08-12T12:18:59+00:00",
      "age_seconds": 687
    },
    {
      "channel": "Kino-Dwij",
      "title": "Не ожидал такой поддержки от команды 🥺 #фильмы #сериалы",
      "url": "https://www.youtube.com/shorts/8BdRQ8dhIQo",
      "published_at_utc": "2025-08-12T10:30:05+00:00",
      "age_seconds": 7222
    }
  ]
}